paystation/__init__.py
paystation/client.py
paystation/exceptions.py
paystation_python_sdk-0.1.1.dist-info/METADATA
paystation_python_sdk-0.1.1.dist-info/WHEEL
paystation_python_sdk-0.1.1.dist-info/top_level.txt
paystation_python_sdk-0.1.1.dist-info/RECORD
