Metadata-Version: 2.4
Name: paystation-python-sdk
Version: 0.1.1
Summary: A Python SDK for the PayStation Bangladesh payment gateway.
Home-page: https://github.com/h-azad/paystation-python-sdk
Author: Hossain Azad
Author-email: me-azad@proton.me
Classifier: Programming Language :: Python :: 3
Classifier: License :: OSI Approved :: MIT License
Classifier: Operating System :: OS Independent
Requires-Python: >=3.6
Requires-Dist: requests
Dynamic: author
Dynamic: author-email
Dynamic: classifier
Dynamic: description
Dynamic: description-content-type
Dynamic: home-page
Dynamic: requires-dist
Dynamic: requires-python
Dynamic: summary
